mongo2pq/__init__.py
mongo2pq/config.py
mongo2pq/exceptions.py
mongo2pq/extract_load.py
mongo2pq/main.py
mongo2pq/mongo.py
mongo2pq/schema.py
mongo2pq/types.py
mongo2pq-0.1.0.dist-info/LICENSE
mongo2pq-0.1.0.dist-info/METADATA
mongo2pq-0.1.0.dist-info/WHEEL
mongo2pq-0.1.0.dist-info/entry_points.txt
mongo2pq-0.1.0.dist-info/RECORD
