Metadata-Version: 2.1
Name: mongo2pq
Version: 0.1.0
Summary: 
Author: Tadeas Uhlir
Author-email: tadeas.uhlir@gmail.com
Requires-Python: >=3.11,<4.0
Classifier: Programming Language :: Python :: 3
Classifier: Programming Language :: Python :: 3.11
Classifier: Programming Language :: Python :: 3.12
Requires-Dist: motor (>=3.3.1,<4.0.0)
Requires-Dist: pyarrow (>=13.0.0,<14.0.0)
Requires-Dist: pymongo (>=4.5.0,<5.0.0)
Requires-Dist: pyyaml (>=6.0.1,<7.0.0)
Requires-Dist: tqdm (>=4.66.1,<5.0.0)
